[
  {
    "slug": "how-to-grab-hp-enduser-tool-log-",
    "claim": "以下是如何抓取 HP EndUser Tool 日誌的詳細說明:",
    "tier": "Derived",
    "evidence_score": 3,
    "wave_id": 3,
    "batch_id": "batch_2026-04-15T09-15-12-351Z"
  },
  {
    "slug": "how-to-grab-hp-enduser-tool-log-",
    "claim": "1. 開啟 HP EndUser Tool 目錄中的 `HPFwUpdate.ini` 檔案。",
    "tier": "Explicit",
    "evidence_score": 6,
    "wave_id": 3,
    "batch_id": "batch_2026-04-15T09-15-12-351Z"
  },
  {
    "slug": "how-to-grab-hp-enduser-tool-log-",
    "claim": "2. 在 `HPFwUpdate.ini` 檔案中新增以下參數:",
    "tier": "Derived",
    "evidence_score": 2,
    "wave_id": 3,
    "batch_id": "batch_2026-04-15T09-15-12-351Z"
  },
  {
    "slug": "how-to-grab-hp-enduser-tool-log-",
    "claim": "3. 執行 HP EndUser Tool。",
    "tier": "Explicit",
    "evidence_score": 4,
    "wave_id": 3,
    "batch_id": "batch_2026-04-15T09-15-12-351Z"
  },
  {
    "slug": "how-to-grab-hp-enduser-tool-log-",
    "claim": "4. 將 HP EndUser Tool 目錄中的日誌檔目錄裡面的日誌檔寄給我們分析。",
    "tier": "Derived",
    "evidence_score": 3,
    "wave_id": 3,
    "batch_id": "batch_2026-04-15T09-15-12-351Z"
  },
  {
    "slug": "how-to-grab-hp-enduser-tool-log-",
    "claim": "1. [Code Sign Flow](code-sign/code-sign-flow.html)",
    "tier": "Explicit",
    "evidence_score": 8,
    "wave_id": 3,
    "batch_id": "batch_2026-04-15T09-15-12-351Z"
  },
  {
    "slug": "how-to-grab-hp-enduser-tool-log-",
    "claim": "- 說明 Genesys Logic 的 code sign 流程，包括使用 OpenSSL、Token 或 HSM 等方式進行簽章。",
    "tier": "Explicit",
    "evidence_score": 8,
    "wave_id": 3,
    "batch_id": "batch_2026-04-15T09-15-12-351Z"
  },
  {
    "slug": "how-to-grab-hp-enduser-tool-log-",
    "claim": "2. [HID Code Sign 記錄](code-sign/hid-code-sign-記錄.html)",
    "tier": "Explicit",
    "evidence_score": 10,
    "wave_id": 3,
    "batch_id": "batch_2026-04-15T09-15-12-351Z"
  },
  {
    "slug": "how-to-grab-hp-enduser-tool-log-",
    "claim": "- 記錄 HID 裝置的 code sign 相關資訊，包括更新協定、工具和測試、執行中的問題和待討論事項。",
    "tier": "Explicit",
    "evidence_score": 4,
    "wave_id": 3,
    "batch_id": "batch_2026-04-15T09-15-12-351Z"
  },
  {
    "slug": "how-to-grab-hp-enduser-tool-log-",
    "claim": "3. [HP Monitor Code Sign Update Flow](code-sign/hp-monitor-code-sign-update-flow.html)",
    "tier": "Explicit",
    "evidence_score": 14,
    "wave_id": 3,
    "batch_id": "batch_2026-04-15T09-15-12-351Z"
  },
  {
    "slug": "how-to-grab-hp-enduser-tool-log-",
    "claim": "- 詳細說明 HP 顯示器的 code sign 更新流程，包括 ISP Tool 與 Hub Firmware 的初始化交握機制，以及不同 code sign 模式的更新流程。",
    "tier": "Explicit",
    "evidence_score": 9,
    "wave_id": 3,
    "batch_id": "batch_2026-04-15T09-15-12-351Z"
  }
]